<?xml version="1.0" encoding="UTF-8"?><record_update table="sp_column">
    <sp_column action="INSERT_OR_UPDATE">
        <class_name/>
        <order>4</order>
        <size>3</size>
        <size_lg/>
        <size_sm/>
        <size_xs/>
        <sp_row display_value="1">6f6b0322db573b8049ac7e7dbf9619b6</sp_row>
        <sys_class_name>sp_column</sys_class_name>
        <sys_created_by>admin</sys_created_by>
        <sys_created_on>2019-08-19 13:24:59</sys_created_on>
        <sys_id>276b0762db573b8049ac7e7dbf961938</sys_id>
        <sys_mod_count>0</sys_mod_count>
        <sys_name>4</sys_name>
        <sys_package display_value="World Builder" source="x_262366_wld_bldr">b3fcc508dbf3130049ac7e7dbf96195b</sys_package>
        <sys_policy/>
        <sys_scope display_value="World Builder">b3fcc508dbf3130049ac7e7dbf96195b</sys_scope>
        <sys_update_name>sp_column_276b0762db573b8049ac7e7dbf961938</sys_update_name>
        <sys_updated_by>admin</sys_updated_by>
        <sys_updated_on>2019-08-19 13:24:59</sys_updated_on>
    </sp_column>
</record_update>
